kahi_ror_affiliations/Kahi_ror_affiliations.py
kahi_ror_affiliations/__init__.py
kahi_ror_affiliations/_version.py
Kahi_ror_affiliations-0.1.4.dist-info/LICENSE
Kahi_ror_affiliations-0.1.4.dist-info/METADATA
Kahi_ror_affiliations-0.1.4.dist-info/WHEEL
Kahi_ror_affiliations-0.1.4.dist-info/top_level.txt
Kahi_ror_affiliations-0.1.4.dist-info/RECORD
